{"id":"riveria_ljos_alf_nine_hell","title":"Nine Hell","name":"Riveria Ljos Alf","type":"healer_type","stars":3,"limited":false,"stats":{"hp":[1186,0,0,0,0,2171],"mp":[156,0,0,0,0,236],"physical_attack":[124,0,0,0,0,316],"magic_attack":[296,0,0,0,0,716],"defense":[86,0,0,0,0,218],"strength":[124,0,0,0,0,316],"endurance":[86,0,0,0,0,218],"dexterity":[218,0,0,0,0,536],"agility":[167,0,0,0,0,417],"magic":[296,0,0,0,0,716]},"skills":{"special":{"name":"Special Placeholder","effects":[{"target":"self","attribute":"strength","modifier":"+0%"}]},
	"combat":[{"name":"Skill 1 Placeholder","effects":[{"target":"self","attribute":"strength","modifier":"+0%"}]},{"name":"Skill 2 Placeholder","effects":[{"target":"self","attribute":"strength","modifier":"+0%"}]},{"name":"Skill 3 Placeholder","effects":[{"target":"self","attribute":"strength","modifier":"+0%"}]}],
	"development":[{"name":"Placeholder: I","effects":[{"attribute":"dexterity","modifier":"+10%"}]},{"name":"PlaceholderTwo: I","effects":[{"attribute":"agility","modifier":"+10%"}]}]}}